radicale_ldap_auth/__init__.py
radicale_ldap_auth-0.0.3.dist-info/LICENSE
radicale_ldap_auth-0.0.3.dist-info/METADATA
radicale_ldap_auth-0.0.3.dist-info/WHEEL
radicale_ldap_auth-0.0.3.dist-info/top_level.txt
radicale_ldap_auth-0.0.3.dist-info/RECORD
